Resilience/__init.py__.py
Resilience/models.py
OpenSafe-0.0.1.dist-info/LICENSE
OpenSafe-0.0.1.dist-info/METADATA
OpenSafe-0.0.1.dist-info/WHEEL
OpenSafe-0.0.1.dist-info/top_level.txt
OpenSafe-0.0.1.dist-info/RECORD
